one/__init__.py
one/api.py
one/converters.py
one/files.py
one/models.py
one/params.py
one/pd_accessors.py
one/registration.py
one/util.py
one/webclient.py
one/alf/__init__.py
one/alf/cache.py
one/alf/exceptions.py
one/alf/files.py
one/alf/io.py
one/alf/migrations.py
one/alf/spec.py
one/remote/__init__.py
one/remote/base.py
one_haisslab-1.3.4.dist-info/licenses/LICENSE
one_haisslab-1.3.4.dist-info/licenses/LICENSE copy
one_haisslab-1.3.4.dist-info/METADATA
one_haisslab-1.3.4.dist-info/WHEEL
one_haisslab-1.3.4.dist-info/top_level.txt
one_haisslab-1.3.4.dist-info/RECORD
