Metadata-Version: 2.4
Name: one-haisslab
Version: 1.3.4
Summary: Alyx Connector, based on the Open Neurophysiology Environment
Author-email: Timothé Jost-Mousseau <timothe.jost-mousseau@pasteur.fr>
Maintainer-email: Timothé Jost-Mousseau <timothe.jost-mousseau@pasteur.fr>
License: MIT
Project-URL: homepage, https://gitlab.pasteur.fr/haisslab/data-management/ONE
Project-URL: repository, https://gitlab.pasteur.fr/haisslab/data-management/ONE
Project-URL: documentation, https://gitlab.pasteur.fr/haisslab/data-management/ONE
Requires-Python: >=3.10
License-File: LICENSE
License-File: LICENSE copy
Requires-Dist: iblutil>=1.7.0
Requires-Dist: ipython>=8.16.1
Requires-Dist: natsort>=8.4.0
Requires-Dist: numpy>=1.25.2
Requires-Dist: packaging>=23.2
Requires-Dist: pandas>=2.1.4
Requires-Dist: PyYAML>=6.0.1
Requires-Dist: PyYAML>=6.0.1
Requires-Dist: Requests>=2.31.0
Requires-Dist: tqdm>=4.66.1
Requires-Dist: pint
Requires-Dist: rich
Dynamic: license-file
